pwbmutils/__init__.py
pwbmutils/example_task.py
pwbmutils/interface_direct_writer.py
pwbmutils/interface_reader.py
pwbmutils/interface_task.py
pwbmutils/interface_writer.py
pwbmutils/map_target.py
pwbmutils/pwbm_task.py
pwbmutils/statistics.py
pwbmutils/test.py
pwbmutils-0.96.dist-info/METADATA
pwbmutils-0.96.dist-info/WHEEL
pwbmutils-0.96.dist-info/top_level.txt
pwbmutils-0.96.dist-info/RECORD
