Metadata-Version: 2.1
Name: pwbmutils
Version: 0.96
Summary: Collection of cross-component utility functions
Home-page: https://github.com/PennWhartonBudgetModel/Utilities
Author: Penn Wharton Budget Model
Author-email: UNKNOWN
License: UNKNOWN
Platform: UNKNOWN
Requires-Dist: luigi
Requires-Dist: pandas
Requires-Dist: matplotlib
Requires-Dist: portalocker
